{"Info": ["CPU: Intel Core i7-13900H\n", "RAM: 32GB (16x 8GB) SO-DIMM DDR5-4800MHz (H\u00e0n li\u1ec1n kh\u00f4ng n\u00e2ng c\u1ea5p \u0111\u01b0\u1ee3c)\n", "\u1ed4 c\u1ee9ng: 1TB SSD M.2 PCIe 4.0x4 NVMe (N\u00e2ng c\u1ea5p thay th\u1ebf)\n", "VGA: NVIDIA\u00ae GeForce RTX\u2122 2000 8GB\n", "M\u00e0n h\u00ecnh: 16\" FHD+ (1920x1200) IPS 500nits Anti-glare\n", "M\u00e0u: X\u00e1m\n", "OS: Windows 11 Pro"], "Detail Info": [["\nM\u00f4 t\u1ea3 chi ti\u1ebft \n"], ["\nH\u00e3ng s\u1ea3n xu\u1ea5t\n", "\nDell\n"], ["\nCh\u1ee7ng lo\u1ea1i\n", "\nWorkstation Mobile Precision 5680\n"], ["\nPart Number\n", "\n71024680\n"], ["\nM\u1ea7u s\u1eafc, ch\u1ea5t li\u1ec7u\n", "\nX\u00e1m (Titan Gray)\n"], ["\nB\u1ed9 vi x\u1eed l\u00fd\n", "\nIntel Core i9-13900H, vPro Enterprise (24MB Cache, 14 Cores, 20 Threads, 2.6 - 5.4 GHz Turbo, 45W)\n"], ["\nChipset\n", "\n\u00a0\n"], ["\nB\u1ed9 nh\u1edb trong (RAM)\n", "\n32 GB LPDDR5, 6000MT/s (2 x 16 GB)\n"], ["\nS\u1ed1 khe c\u1eafm RAM\n", "\n2\n"], ["\nDung l\u01b0\u1ee3ng RAM t\u1ed1i \u0111a\n", "\n64 GB\n"], ["\nVGA\n", "\nNVIDIA RTX 2000 Ada, 8GB GDDR6\n"], ["\n\u1ed4 c\u1ee9ng\n", "\n1TB, M.2 2280, Gen 4 PCIe NVMe SSD, Class 40\n"], ["\n\u1ed4 quang\n", "\nNo\n"], ["\nCard Reader\n", "\nMicro SD\n"], ["\nB\u1ea3o m\u1eadt, c\u00f4ng ngh\u1ec7\n", "\n\u00a0\n"], ["\nM\u00e0n h\u00ecnh\n", "\n16 inch FHD+ non-touch, 1920 x 1200, 60Hz, 500 nits WLED, 100% DCI-P3, Low BL w/ IR Cam\n"], ["\nWebcam\n", "\nFHD IR camera with narrow FHD+IR w/ XYZ ALS (MIPI), Dual-array microphones\n"], ["\nAudio\n", "\nRealtek ALC711-VD\n2 x Woofers\n2 x Tweeters\n\u00a0\n"], ["\nGiao ti\u1ebfp m\u1ea1ng\n", "\n\u00a0\n"], ["\nGiao ti\u1ebfp kh\u00f4ng d\u00e2y\n", "\nIntel AX211, 2x2 MIMO, 2400 Mbps, 2.4/5/6 GHz, Wi-Fi 6/6E (WiFi 802.11ax), Bluetooth Wireless Intel AX211 WLAN Driver\n"], ["\nC\u00e1c c\u1ed5ng giao ti\u1ebfp\n", "\nOne USB 3.2 Gen 2 Type-C port with DisplayPort 1.4 Alt Mode Two Thunderbolt 4 ports (USB Type-C); One 3.5 mm audio jack; One HDMI 2.0b port\n"], ["\nPin\n", "\n6 Cell, 100Wh\n"], ["\nK\u00edch th\u01b0\u1edbc (r\u1ed9ng x d\u00e0i x cao)\n", "\n26.17 x 353.68 x 240.27 (mm)\n"], ["\nC\u00e2n n\u1eb7ng\n", "\n1.905 kg\n"], ["\nH\u1ec7 \u0111i\u1ec1u h\u00e0nh\n", "\nUbuntu\n"], ["\nPh\u1ee5 ki\u1ec7n \u0111i k\u00e8m\n", "\nAC Adapter\n"]], "Price": "96999000", "Warrant": "B\u1ea3o h\u00e0nh 36 Th\u00e1ng (Ri\u00eang Pin, Adapter BH 12 th\u00e1ng)", "Link": "https://hacom.vn/laptop-dell-mobile-precision-workstation-5680-vpro-enterprise-71024680-i9-13900h-32gb-ram-1tb-ssd-rtx2000-ada-8gb-16-inch-fhd-win-11-pro-xam"}